afinipy/__init__.py
afinipy/afinipy.py
afinipy/base.py
afinipy/directory.py
afinipy/exceptions.py
afinipy/exclusion_paser.py
afinipy/module.py
afinipy/path_funcs.py
afinipy/utils.py
afinipy-0.1.3.dist-info/LICENSE
afinipy-0.1.3.dist-info/METADATA
afinipy-0.1.3.dist-info/WHEEL
afinipy-0.1.3.dist-info/entry_points.txt
afinipy-0.1.3.dist-info/top_level.txt
afinipy-0.1.3.dist-info/RECORD
