Metadata-Version: 2.1
Name: afinipy
Version: 0.1.3
Summary: Automated init builder
Home-page: UNKNOWN
Author: Ralph Urlus
Author-email: rurlus.dev@gmail.com
License: UNKNOWN
Project-URL: Bug Reports, https://github.com/RUrlus/afinipy/issues
Project-URL: Source, https://github.com/RUrlus/afinipy
Keywords: init development
Platform: UNKNOWN
Classifier: Development Status :: 4 - Beta
Classifier: Intended Audience :: Developers
Classifier: Topic :: Software Development :: Build Tools
Classifier: License :: OSI Approved :: GNU General Public License v3 (GPLv3)
Classifier: Programming Language :: Python :: 2
Classifier: Programming Language :: Python :: 2.7
Classifier: Programming Language :: Python :: 3
Classifier: Programming Language :: Python :: 3.4
Classifier: Programming Language :: Python :: 3.5
Classifier: Programming Language :: Python :: 3.6
Classifier: Programming Language :: Python :: 3.7
Requires-Python: >=2.7, !=3.0.*, !=3.1.*, !=3.2.*, !=3.3.*, <4
Requires-Dist: Click
